pygame_tools.py
pygame_tools-0.1.6.dist-info/LICENSE
pygame_tools-0.1.6.dist-info/METADATA
pygame_tools-0.1.6.dist-info/WHEEL
pygame_tools-0.1.6.dist-info/top_level.txt
pygame_tools-0.1.6.dist-info/RECORD
