Metadata-Version: 2.1
Name: pygame-tools
Version: 0.1.6
Summary: A package to make creating pygame applications much easier
Home-page: https://github.com/shanemcdo/pygame_tools
Author: shanemcdo (Shane McDonough)
License: MIT
Keywords: pygame 2d-game video-game
License-File: LICENSE
Requires-Dist: pygame
Requires-Dist: recordclass
